Musicreater/__init__.py
Musicreater/constants.py
Musicreater/exceptions.py
Musicreater/experiment.py
Musicreater/magicmain.py
Musicreater/main.py
Musicreater/plugin/__init__.py
Musicreater/plugin/addonpack/__init__.py
Musicreater/plugin/addonpack/main.py
Musicreater/plugin/archive.py
Musicreater/plugin/bdx.py
Musicreater/plugin/bdxfile/__init__.py
Musicreater/plugin/bdxfile/main.py
Musicreater/plugin/common.py
Musicreater/plugin/main.py
Musicreater/plugin/mcstructfile/__init__.py
Musicreater/plugin/mcstructfile/main.py
Musicreater/plugin/mcstructure.py
Musicreater/plugin/noteblock.py
Musicreater/plugin/schematic.py
Musicreater/plugin/schematic/__init__.py
Musicreater/plugin/schematic/main.py
Musicreater/plugin/websocket/__init__.py
Musicreater/plugin/websocket/main.py
Musicreater/subclass.py
Musicreater/types.py
Musicreater/utils.py
musicreater-2.4.2.3.dist-info/METADATA
musicreater-2.4.2.3.dist-info/WHEEL
musicreater-2.4.2.3.dist-info/entry_points.txt
musicreater-2.4.2.3.dist-info/licenses/LICENSE.md
musicreater-2.4.2.3.dist-info/RECORD
