Metadata-Version: 2.1
Name: Musicreater
Version: 2.4.2.3
Summary: A free open source library used for dealing with **Minecraft** digital musics.
Keywords: midi,minecraft,minecraft: bedrock edition
Author: 金羿Eilles, 玉衡Alioth, 鱼旧梦ElapsingDreams
Author-Email: =?utf-8?b?552/5LmQ57uE57uHIFRyaU1P?= <TriM-Organization@hotmail.com>
Maintainer-Email: =?utf-8?b?6YeR576/RWlsbGVz?= <EillesWan@outlook.com>
License: # 汉钰律许可协议，第一版
Classifier: Intended Audience :: Developers
Classifier: Natural Language :: Chinese (Simplified)
Classifier: Operating System :: OS Independent
Classifier: Topic :: Software Development :: Libraries
Classifier: Programming Language :: Python
Classifier: Programming Language :: Python :: 3
Classifier: Topic :: Multimedia
Classifier: Topic :: Multimedia :: Sound/Audio :: MIDI
Project-URL: Repository, https://gitee.com/TriM-Organization/Musicreater
Project-URL: Issues, https://gitee.com/TriM-Organization/Musicreater/issues
Project-URL: Mirror-Repository, https://github.com/TriM-Organization/Musicreater
Project-URL: Mirror-Issues, https://github.com/TriM-Organization/Musicreater/issues
Requires-Python: <4.0,>=3.8
Requires-Dist: mido>=1.3
Requires-Dist: xxhash>=3
Provides-Extra: full
Requires-Dist: TrimMCStruct<=0.0.5.9; extra == "full"
Requires-Dist: brotli>=1.0.0; extra == "full"
Provides-Extra: dev
Requires-Dist: TrimMCStruct<=0.0.5.9; extra == "dev"
Requires-Dist: brotli>=1.0.0; extra == "dev"
Requires-Dist: dill; extra == "dev"
Requires-Dist: rich; extra == "dev"
Requires-Dist: pyinstaller; extra == "dev"
Requires-Dist: twine; extra == "dev"
